databot/__init__.py
databot/bdata.py
databot/bot.py
databot/botframe.py
databot/config.py
databot/flow.py
databot/node.py
databot/persis.py
databot/queue.py
databot/db/__init__.py
databot/db/aiofile.py
databot/db/mysql.py
databot/http/__init__.py
databot/http/http.py
databot/http/parse.py
databot-0.1.8.dist-info/METADATA
databot-0.1.8.dist-info/RECORD
databot-0.1.8.dist-info/WHEEL
databot-0.1.8.dist-info/top_level.txt
