Metadata-Version: 2.1
Name: databot
Version: 0.1.8
Summary: data flow programming framework with asyncio 
Home-page: https://github.com/kkyx/databot
Author: Guojian Li
Author-email: guojianlee@gmail.com
License: BSD
Platform: UNKNOWN
Classifier: Development Status :: 3 - Alpha
Classifier: Intended Audience :: Developers
Classifier: License :: OSI Approved :: BSD License
Classifier: Programming Language :: Python :: 3
Requires-Python: >=3.6.5
Requires-Dist: aiohttp (>=3.3.0)
Requires-Dist: aiomysql (>=0.0.19)
Requires-Dist: graphviz
